unicards
