Metadata-Version: 1.1
Name: unicards
Version: 0.6
Summary: Convert strings into unicode playing cards
Home-page: http://github.com/lmacken/unicards
Author: Luke Macken
Author-email: lmacken@redhat.com
License: ASL 2.0
Keywords: python unicode cards poker deck
Platform: UNKNOWN
Classifier: Development Status :: 4 - Beta
Classifier: Intended Audience :: Developers
Classifier: Programming Language :: Python :: 2.7
Classifier: Programming Language :: Python :: 3.3
Classifier: Topic :: Software Development
Classifier: Topic :: Utilities
Classifier: Topic :: Games/Entertainment
Classifier: License :: OSI Approved :: Apache Software License
